goap/__init__.py
goap/action.py
goap/algo/__init__.py
goap/algo/astar.py
goap/planner/__init__.py
goap/planner/plan.py
goap/planner/regressive_astar.py
goap/priority_queue.py
goap/visualise.py
goap_ai-2.0.0.dist-info/WHEEL
goap_ai-2.0.0.dist-info/METADATA
goap_ai-2.0.0.dist-info/RECORD
